graphwatch/__init__.py
graphwatch/__main__.py
graphwatch/_version.py
graphwatch/graphwatch.py
graphwatch/assets/vis.css
graphwatch/assets/vis.js
graphwatch-0.0.4.dist-info/METADATA
graphwatch-0.0.4.dist-info/RECORD
graphwatch-0.0.4.dist-info/WHEEL
graphwatch-0.0.4.dist-info/top_level.txt
graphwatch-0.0.4.dist-info/zip-safe
