Metadata-Version: 2.1
Name: graphwatch
Version: 0.0.4
Summary: A web app showing a dot graph evolutions.
Home-page: UNKNOWN
Author: Samuel Loury
Author-email: konubinixweb@gmail.com
License: UNKNOWN
Platform: UNKNOWN
Requires-Dist: flexx
Requires-Dist: pydot
Requires-Dist: networkx
